simple_registry_api/AuthorizationService.py
simple_registry_api/Registry.py
simple_registry_api/_BaseClient.py
simple_registry_api/__init__.py
simple_registry_api-1.2.0.dist-info/LICENSE
simple_registry_api-1.2.0.dist-info/METADATA
simple_registry_api-1.2.0.dist-info/NOTICE
simple_registry_api-1.2.0.dist-info/WHEEL
simple_registry_api-1.2.0.dist-info/top_level.txt
simple_registry_api-1.2.0.dist-info/RECORD
